nse_quadratic_mats/__init__.py
nse_quadratic_mats/conv_tensor_utils.py
nse_quadratic_mats/visualization_utils.py
nse_quadratic_mats-0.0.3.dist-info/METADATA
nse_quadratic_mats-0.0.3.dist-info/WHEEL
nse_quadratic_mats-0.0.3.dist-info/top_level.txt
nse_quadratic_mats-0.0.3.dist-info/RECORD
