Metadata-Version: 2.1
Name: nse-quadratic-mats
Version: 0.0.3
Summary: basic routines for treating the NSE with the convection as a tensor
Home-page: https://gitlab.mpi-magdeburg.mpg.de/heiland/nse-quadratic-mats
Author: Jan Heiland
Author-email: jnhlnd@gmail.com
License: MIT
Platform: UNKNOWN
Classifier: Programming Language :: Python :: 3
Classifier: License :: OSI Approved :: GNU General Public License v3 (GPLv3)
Classifier: Operating System :: OS Independent
Requires-Dist: numpy
Requires-Dist: scipy
